ando/__init__.py
ando/_init_.py
ando/_version.py
ando/checker.py
ando/engine.py
ando/error.py
ando/rules/__init__.py
ando/rules/derivatives_rules.json
ando/rules/experiment_rules.json
ando/rules/isAndo_rules.json
ando/rules/metadata_rules.json
ando/rules/rawdata_rules.json
ando/rules/session_rules.json
ando/rules/subject_rules.json
ando/tests/__init__.py
ando/tests/test_Rules.py
ando/tests/test_engine.py
ando/tests/test_isAnDO.py
ando/tests/test_parse_all_path.py
AnDOChecker-0.3.2.dist-info/LICENSE
AnDOChecker-0.3.2.dist-info/METADATA
AnDOChecker-0.3.2.dist-info/WHEEL
AnDOChecker-0.3.2.dist-info/entry_points.txt
AnDOChecker-0.3.2.dist-info/top_level.txt
AnDOChecker-0.3.2.dist-info/RECORD
