Metadata-Version: 2.1
Name: AnDOChecker
Version: 0.3.2
Summary: Checks the validity of a directory with respect to the ANimal Data Organization (ANDO) specifications 
Home-page: UNKNOWN
Author: Jeremy Garcia, Sylvain Takerkart
License: MIT
Platform: UNKNOWN
Requires-Python: >=3.6
Requires-Dist: flake8
Requires-Dist: pytest
